MANIFEST.in
README.md
setup.py
autocomplete_trie/TestUtilities.py
autocomplete_trie/Trie.py
autocomplete_trie/TrieUtilities.py
autocomplete_trie/__init__.py
autocomplete_trie.egg-info/PKG-INFO
autocomplete_trie.egg-info/SOURCES.txt
autocomplete_trie.egg-info/dependency_links.txt
autocomplete_trie.egg-info/top_level.txt