Metadata-Version: 1.1
Name: autocomplete-trie
Version: 0.3
Summary: A database that supports fast autocomplete. Implemented using a trie.
Home-page: https://github.com/36-750/assignments-Timothy-Barry/tree/master/autocomplete-me
Author: Tim Barry
Author-email: timothybarry@cmu.edu
License: UNKNOWN
Platform: UNKNOWN
Classifier: Programming Language :: Python :: 3
Classifier: License :: OSI Approved :: MIT License
Classifier: Operating System :: OS Independent
